Workbook

Sheet Notes
A1: Notes:
A2: Quick Start Guide:
A3: 1. Add all Purchase entries first.
A4: 2. Add Sales only after item exists in Purchases.
A5: 3. Mark sale status as Completed when payment is fully received.
A6: 4. Enter settlements only when real money is exchanged.
A8: 5. Check Summary tab for final Pay/Receive for each partner.
A10: 1. Totals reference existing Purchases and Sales sheets directly.
A11: 2. Profit is only calculated on Completed sales (Status = "Completed").
A12: 3. Partner details and settlements are maintained in PartnerShares and Cash Pool sheets.
A14: 5. Cash Pool Logic:
A15: - Cash Pool shows partner contributions & withdrawals relative to each other.
... A203: 13. Profit settlement is not required when Cash Pool is regularly settled; Profit summary is kept only for FYI.

Sheet Summary
A1: Chiraath - Business Summary
A3: Total Purchases (₹) | B3: =SUM(Purchases!C:C) -> 294436 | E3: Partner | F3: Share % (Cash/Profit)
A4: Total Sales (₹ - Completed only) | B4: =SUMIFS(Sales!C:C, Sales!I:I, "Completed") -> 256492 | E4: =PartnerShares!A3 -> Rajna | F4: =PartnerShares!B3 -> 0.3334
A5: Total Sales (₹ - All rows) | B5: =SUM(Sales!C:C) -> 261022 | E5: =PartnerShares!A4 -> Anoop | F5: =PartnerShares!B4 -> 0.3332
A6: Profit / (Loss) (₹, on Completed sales only) | B6: =B4-B3 -> -37944 | E6: =PartnerShares!A5 -> Rameez | F6: =PartnerShares!B5 -> 0.3334
A7: Profit Status | B7: =IF(B6>0,"Profit","No Profit (or Loss)") -> No Profit (or Loss)
A9: Partner | B9: Net Position After Settlements (₹)
A10: Rajna | B10: =PartnerShares!H8 -> 10205.327
A11: Anoop | B11: =PartnerShares!H9 -> -4602.6633
A12: Rameez | B12: =PartnerShares!H10 -> -5602.6633
A16: Contribution Summary
A17: Partner | B17: Total Paid (₹) | C17: Target (Equal 1/3) | D17: Excess Paid (Refund Due)(₹) | E17: Settled So Far | F17: Pending Balance (+ Receive / - Pay) | G17: Action
A18: =PartnerShares!A8 -> Rajna | B18: =PartnerShares!B8 -> 126654 | C18: =PartnerShares!C8 -> 98145.333 | D18: =PartnerShares!D8 -> 28508.667 | E18: =IFERROR(SUMIFS(PartnerShares!$E$14:$E$500,PartnerShares!$D$14:$D$500,$A18,PartnerShares!$B$14:$B$500,"Contribution"),0)-IFERROR(SUMIFS(PartnerShares!$E$14:$E$500,PartnerShares!$C$14:$C$500,$A18,PartnerShares!$B$14:$B$500,"Contribution"),0) -> 18303.34 | F18: =D18-E18 -> 10205.327 | G18: =IF(ROUND(F18,0)>0,"Receive ₹"&TEXT(ABS(F18),"#,##0"),IF(ROUND(F18,0)<0,"Pay ₹"&TEXT(ABS(F18),"#,##0"),"✓ Settled")) -> Receive ₹10,205
A19: =PartnerShares!A9 -> Anoop | B19: =PartnerShares!B9 -> 135182 | C19: =PartnerShares!C9 -> 98145.333 | D19: =PartnerShares!D9 -> 37036.667 | E19: =IFERROR(SUMIFS(PartnerShares!$E$14:$E$500,PartnerShares!$D$14:$D$500,$A19,PartnerShares!$B$14:$B$500,"Contribution"),0)-IFERROR(SUMIFS(PartnerShares!$E$14:$E$500,PartnerShares!$C$14:$C$500,$A19,PartnerShares!$B$14:$B$500,"Contribution"),0) -> 41639.33 | F19: =D19-E19 -> -4602.6633 | G19: =IF(ROUND(F19,0)>0,"Receive ₹"&TEXT(ABS(F19),"#,##0"),IF(ROUND(F19,0)<0,"Pay ₹"&TEXT(ABS(F19),"#,##0"),"✓ Settled")) -> Pay ₹4,603
A20: =PartnerShares!A10 -> Rameez | B20: =PartnerShares!B10 -> 32600 | C20: =PartnerShares!C10 -> 98145.333 | D20: =PartnerShares!D10 -> -65545.333 | E20: =IFERROR(SUMIFS(PartnerShares!$E$14:$E$500,PartnerShares!$D$14:$D$500,$A20,PartnerShares!$B$14:$B$500,"Contribution"),0)-IFERROR(SUMIFS(PartnerShares!$E$14:$E$500,PartnerShares!$C$14:$C$500,$A20,PartnerShares!$B$14:$B$500,"Contribution"),0) -> -59942.67 | F20: =D20-E20 -> -5602.6633 | G20: =IF(ROUND(F20,0)>0,"Receive ₹"&TEXT(ABS(F20),"#,##0"),IF(ROUND(F20,0)<0,"Pay ₹"&TEXT(ABS(F20),"#,##0"),"✓ Settled")) -> Pay ₹5,603
A24: Cash Pool Summary
A25: Partner | B25: Cash Collected (₹) | C25: Target Cash (₹) | D25: Excess Cash Held (Debt to Pool)(₹) | E25: Cash Transferred So Far | F25: Pending Balance (+ Pay / - Receive) | G25: Action
A26: ='Cash Pool'!A4 -> Rajna | B26: ='Cash Pool'!B4 -> 235543 | C26: ='Cash Pool'!D4 -> 85514.433 | D26: ='Cash Pool'!E4 -> 150028.57 | E26: ='Cash Pool'!F4 -> -137310.03 | F26: ='Cash Pool'!G4 -> 12718.541 | G26: =IF(ROUND(F26,0)>0,"Pay ₹"&TEXT(ABS(F26),"#,##0"),IF(ROUND(F26,0)<0,"Receive ₹"&TEXT(ABS(F26),"#,##0"),"✓ Settled")) -> Pay ₹12,719
A27: ='Cash Pool'!A5 -> Anoop | B27: ='Cash Pool'!B5 -> 8419 | C27: ='Cash Pool'!D5 -> 85463.134 | D27: ='Cash Pool'!E5 -> -77044.134 | E27: ='Cash Pool'!F5 -> 71587.042 | F27: ='Cash Pool'!G5 -> -5457.0924 | G27: =IF(ROUND(F27,0)>0,"Pay ₹"&TEXT(ABS(F27),"#,##0"),IF(ROUND(F27,0)<0,"Receive ₹"&TEXT(ABS(F27),"#,##0"),"✓ Settled")) -> Receive ₹5,457
A28: ='Cash Pool'!A6 -> Rameez | B28: ='Cash Pool'!B6 -> 12530 | C28: ='Cash Pool'!D6 -> 85514.433 | D28: ='Cash Pool'!E6 -> -72984.433 | E28: ='Cash Pool'!F6 -> 65722.984 | F28: ='Cash Pool'!G6 -> -7261.4488 | G28: =IF(ROUND(F28,0)>0,"Pay ₹"&TEXT(ABS(F28),"#,##0"),IF(ROUND(F28,0)<0,"Receive ₹"&TEXT(ABS(F28),"#,##0"),"✓ Settled")) -> Receive ₹7,261
A32: Profit Summary
A33: Partner | B33: Profit Share (₹)
A34: =PartnerShares!A8 -> Rajna | B34: =PartnerShares!E8 -> 0
A35: =PartnerShares!A9 -> Anoop | B35: =PartnerShares!E9 -> 0
A36: =PartnerShares!A10 -> Rameez | B36: =PartnerShares!E10 -> 0

Sheet Dashboard
A1: Chiraath Boutique – Business Dashboard
A3: Last Updated | B3: =TODAY() -> 46123
A5: Total Purchases (₹) | B5: =Summary!B3 -> 294436 | D5: Total Sales (₹ - Completed) | E5: =Summary!B4 -> 256492
A6: Total Profit (₹) | B6: =Summary!B6 -> -37944 | D6: Pending Stock Value (₹) | E6: =SUMIFS(INVENTORY!K:K, INVENTORY!N:N, "<>Sold Out") -> 112204.07
A7: Filter Year: | B7: 2026
A9: Month | B9: Purchases (₹) | C9: Sales (₹) | D9: Net Cash Flow (₹) | F9: Metric | G9: Qty
A10: Jan | B10: =IFERROR(SUMPRODUCT((TEXT(Purchases!$A$2:$A$998,"MMM")=$A10)*(YEAR(Purchases!$A$2:$A$998)=$B$7)*Purchases!$C$2:$C$998),0) -> 47311 | C10: =IFERROR(SUMPRODUCT((TEXT(Sales!$A$2:$A$997,"MMM")=$A10)*(YEAR(Sales!$A$2:$A$997)=$B$7)*Sales!$C$2:$C$997),0) -> 45448 | D10: =C10-B10 -> -1863 | F10: Qty Sold | G10: =SUM(INVENTORY!F:F) -> 207
A11: Feb | B11: =IFERROR(SUMPRODUCT((TEXT(Purchases!$A$2:$A$998,"MMM")=$A11)*(YEAR(Purchases!$A$2:$A$998)=$B$7)*Purchases!$C$2:$C$998),0) -> 4790 | C11: =IFERROR(SUMPRODUCT((TEXT(Sales!$A$2:$A$997,"MMM")=$A11)*(YEAR(Sales!$A$2:$A$997)=$B$7)*Sales!$C$2:$C$997),0) -> 19089 | D11: =C11-B11 -> 14299 | F11: Qty Pending | G11: =SUM(INVENTORY!G:G) -> 127
A12: Mar | B12: =IFERROR(SUMPRODUCT((TEXT(Purchases!$A$2:$A$998,"MMM")=$A12)*(YEAR(Purchases!$A$2:$A$998)=$B$7)*Purchases!$C$2:$C$998),0) -> 22172 | C12: =IFERROR(SUMPRODUCT((TEXT(Sales!$A$2:$A$997,"MMM")=$A12)*(YEAR(Sales!$A$2:$A$997)=$B$7)*Sales!$C$2:$C$997),0) -> 16548 | D12: =C12-B12 -> -5624
A13: Apr | B13: =IFERROR(SUMPRODUCT((TEXT(Purchases!$A$2:$A$998,"MMM")=$A13)*(YEAR(Purchases!$A$2:$A$998)=$B$7)*Purchases!$C$2:$C$998),0) -> 15145 | C13: =IFERROR(SUMPRODUCT((TEXT(Sales!$A$2:$A$997,"MMM")=$A13)*(YEAR(Sales!$A$2:$A$997)=$B$7)*Sales!$C$2:$C$997),0) -> 13910 | D13: =C13-B13 -> -1235
A14: May | B14: =IFERROR(SUMPRODUCT((TEXT(Purchases!$A$2:$A$998,"MMM")=$A14)*(YEAR(Purchases!$A$2:$A$998)=$B$7)*Purchases!$C$2:$C$998),0) -> 0 | C14: =IFERROR(SUMPRODUCT((TEXT(Sales!$A$2:$A$997,"MMM")=$A14)*(YEAR(Sales!$A$2:$A$997)=$B$7)*Sales!$C$2:$C$997),0) -> 0 | D14: =C14-B14 -> 0
A15: Jun | B15: =IFERROR(SUMPRODUCT((TEXT(Purchases!$A$2:$A$998,"MMM")=$A15)*(YEAR(Purchases!$A$2:$A$998)=$B$7)*Purchases!$C$2:$C$998),0) -> 0 | C15: =IFERROR(SUMPRODUCT((TEXT(Sales!$A$2:$A$997,"MMM")=$A15)*(YEAR(Sales!$A$2:$A$997)=$B$7)*Sales!$C$2:$C$997),0) -> 0 | D15: =C15-B15 -> 0
A16: Jul | B16: =IFERROR(SUMPRODUCT((TEXT(Purchases!$A$2:$A$998,"MMM")=$A16)*(YEAR(Purchases!$A$2:$A$998)=$B$7)*Purchases!$C$2:$C$998),0) -> 0 | C16: =IFERROR(SUMPRODUCT((TEXT(Sales!$A$2:$A$997,"MMM")=$A16)*(YEAR(Sales!$A$2:$A$997)=$B$7)*Sales!$C$2:$C$997),0) -> 0 | D16: =C16-B16 -> 0
A17: Aug | B17: =IFERROR(SUMPRODUCT((TEXT(Purchases!$A$2:$A$998,"MMM")=$A17)*(YEAR(Purchases!$A$2:$A$998)=$B$7)*Purchases!$C$2:$C$998),0) -> 0 | C17: =IFERROR(SUMPRODUCT((TEXT(Sales!$A$2:$A$997,"MMM")=$A17)*(YEAR(Sales!$A$2:$A$997)=$B$7)*Sales!$C$2:$C$997),0) -> 0 | D17: =C17-B17 -> 0
A18: Sep | B18: =IFERROR(SUMPRODUCT((TEXT(Purchases!$A$2:$A$998,"MMM")=$A18)*(YEAR(Purchases!$A$2:$A$998)=$B$7)*Purchases!$C$2:$C$998),0) -> 0 | C18: =IFERROR(SUMPRODUCT((TEXT(Sales!$A$2:$A$997,"MMM")=$A18)*(YEAR(Sales!$A$2:$A$997)=$B$7)*Sales!$C$2:$C$997),0) -> 0 | D18: =C18-B18 -> 0
A19: Oct | B19: =IFERROR(SUMPRODUCT((TEXT(Purchases!$A$2:$A$998,"MMM")=$A19)*(YEAR(Purchases!$A$2:$A$998)=$B$7)*Purchases!$C$2:$C$998),0) -> 0 | C19: =IFERROR(SUMPRODUCT((TEXT(Sales!$A$2:$A$997,"MMM")=$A19)*(YEAR(Sales!$A$2:$A$997)=$B$7)*Sales!$C$2:$C$997),0) -> 0 | D19: =C19-B19 -> 0
A20: Nov | B20: =IFERROR(SUMPRODUCT((TEXT(Purchases!$A$2:$A$998,"MMM")=$A20)*(YEAR(Purchases!$A$2:$A$998)=$B$7)*Purchases!$C$2:$C$998),0) -> 0 | C20: =IFERROR(SUMPRODUCT((TEXT(Sales!$A$2:$A$997,"MMM")=$A20)*(YEAR(Sales!$A$2:$A$997)=$B$7)*Sales!$C$2:$C$997),0) -> 0 | D20: =C20-B20 -> 0
A21: Dec | B21: =IFERROR(SUMPRODUCT((TEXT(Purchases!$A$2:$A$998,"MMM")=$A21)*(YEAR(Purchases!$A$2:$A$998)=$B$7)*Purchases!$C$2:$C$998),0) -> 0 | C21: =IFERROR(SUMPRODUCT((TEXT(Sales!$A$2:$A$997,"MMM")=$A21)*(YEAR(Sales!$A$2:$A$997)=$B$7)*Sales!$C$2:$C$997),0) -> 0 | D21: =C21-B21 -> 0
F46: Category | G46: Qty Sold | H46: Qty Pending | J46: Category | K46: Pending Value (₹)
F47: Saree | G47: =SUMIF(INVENTORY!C:C, F47, INVENTORY!F:F) -> 129 | H47: =SUMIF(INVENTORY!C:C, F47, INVENTORY!G:G) -> 54 | J47: Salwar | K47: {=SUMPRODUCT((INVENTORY!$C$2:$C$477=J47)*(INVENTORY!$D$2:$D$477)*(INVENTORY!$G$2:$G$477))} -> 69946
F48: Salwar | G48: =SUMIF(INVENTORY!C:C, F48, INVENTORY!F:F) -> 76 | H48: =SUMIF(INVENTORY!C:C, F48, INVENTORY!G:G) -> 68 | J48: Saree | K48: {=SUMPRODUCT((INVENTORY!$C$2:$C$477=J48)*(INVENTORY!$D$2:$D$477)*(INVENTORY!$G$2:$G$477))} -> 41509.067
F49: Kurti | G49: =SUMIF(INVENTORY!C:C, F49, INVENTORY!F:F) -> 2 | H49: =SUMIF(INVENTORY!C:C, F49, INVENTORY!G:G) -> 5 | J49: Kurti | K49: {=SUMPRODUCT((INVENTORY!$C$2:$C$477=J49)*(INVENTORY!$D$2:$D$477)*(INVENTORY!$G$2:$G$477))} -> 1829

Sheet Purchases
A1: Date | B1: Partner | C1: Amount (₹) | D1: Notes
A2: 45890 | B2: Rameez | C2: 10650 | D2: Initial contribution
A3: 45890 | B3: Rajna | C3: 55219 | D3: Initial contribution (Anoop transferered 35k)
A4: 45897 | B4: Anoop | C4: 35000 | D4: Initial contribution
A5: 45908 | B5: Rajna | C5: 1250 | D5: Davani for Priya
A6: 45908 | B6: Rajna | C6: 75 | D6: Kannur courier
A7: 45922 | B7: Rameez | C7: 199 | D7: Recharge
A8: 45922 | B8: Rajna | C8: 200 | D8: Courier cover
A9: 45922 | B9: Rajna | C9: 350 | D9: Courier Assam
A10: 45922 | B10: Rajna | C10: 230 | D10: Courier Assam
A11: 45931 | B11: Anoop | C11: 35750 | D11: New purchases Salwars
A12: 45931 | B12: Rajna | C12: 1362 | D12: New purchases Salwars
A13: 45931 | B13: Rajna | C13: 450 | D13: Cotton Saree
... A62: 46122 | B62: Rajna | C62: 166 | D62: Postal charges

Sheet Sales
A1: Date | B1: Customer | C1: Amount (₹) | D1: Payment Method | E1: Partner Received | F1: Size | G1: Color | H1: Comments | I1: Status
A2: 45900 | B2: Chris | C2: 1250 | D2: GPay | E2: Rajna | I2: Completed
A3: 45900 | B3: Susmitha | C3: 1600 | D3: Cash | E3: Rajna | I3: Completed
A4: 45900 | B4: Jisha | C4: 1800 | D4: Cash | E4: Rajna | I4: Completed
A5: 45900 | B5: Sreejesh | C5: 2000 | D5: GPay | E5: Rajna | I5: Completed
A6: 45900 | B6: Latha | C6: 1600 | D6: Cash | E6: Rajna | I6: Completed
A7: 45900 | B7: Beena (Knr) | C7: 750 | D7: GPay | E7: Rajna | I7: Completed
A8: 45900 | B8: Binoy | C8: 3600 | D8: GPay | E8: Rajna | I8: Completed
A9: 45901 | B9: Binoy | C9: 1000 | D9: GPay | E9: Rajna | I9: Completed
A10: 45902 | B10: Suresh (PVB) | C10: 2000 | D10: GPay | E10: Rajna | I10: Completed
A11: 45903 | B11: Raji | C11: 3400 | D11: GPay | E11: Rajna | I11: Completed
A12: 45904 | B12: Divya | C12: 2500 | D12: Karassery Bank | E12: Rajna | I12: Completed
A13: 45905 | B13: Munni | C13: 4000 | D13: GPay | E13: Rajna | I13: Completed
... A53: 45985 | B53: Aasa | C53: 1600 | D53: Gpay | E53: Rajna | I53: Completed
A54: 45986 | B54: Shimna | C54: 4900 | D54: Gpay | E54: Rajna | H54: Anchal 3 salwars | I54: Completed
A55: 45992 | B55: Yaaser | C55: 4500 | D55: Gpay | E55: Rajna | H55: Anchal 3 salwars | I55: Completed
A56: 45992 | B56: Shanu | C56: 1600 | D56: Gpay | E56: Rajna | H56: Chanderi silk salwar | I56: Completed
A57: 45996 | B57: Ranju | C57: 1500 | D57: Gpay | E57: Rajna | H57: Black Salwar (XXL) | I57: Completed
A58: 45996 | B58: Aruna | C58: 7500 | D58: Gpay | E58: Rajna | H58: Silk Saree, Kalyani yellow saree, Banarasi biscuit, Banarasi blue, Pashmina saree, Chanderi violet saree | I58: Completed
A59: 45996 | B59: Malini | C59: 1400 | D59: Cash | E59: Rajna | H59: Banarasi Chikku | I59: Completed
A60: 46007 | B60: Resmi | C60: 699 | D60: Net banking | E60: Rajna | H60: Chanderi blue saree | I60: Completed
A61: 46008 | B61: Jisha | C61: 1400 | D61: Karassery Account | E61: Rajna | F61: L | H61: Maroon - Silk Blend Salwar set | I61: Completed
A62: 46008 | B62: Rishma | C62: 1380 | D62: Gpay | E62: Rajna | H62: Yellow Banarasi | I62: Completed
A63: 46008 | B63: Aasa | C63: 1380 | D63: Gpay | E63: Rajna | H63: Yellow/Green Banarasi | I63: Completed
A64: 46008 | B64: Malini | C64: 700 | D64: Gpay | E64: Rajna | H64: Chanderi rani pink saree | I64: Completed
A65: 46009 | B65: Dona | C65: 2100 | D65: Cash | E65: Rajna | H65: Aanchal green floral & Silk Saree | I65: Completed
A66: 46010 | B66: Jyothi mol | C66: 1380 | D66: Karassery Account | E66: Rajna | H66: Yellow/Green Banarasi | I66: Completed
A67: 46010 | B67: Prema | C67: 1000 | D67: Gpay | E67: Rajna | F67: XXL | H67: Brick Red Salwar Elephant print | I67: Completed
A68: 46011 | B68: Sruthi | C68: 3900 | D68: Gpay | E68: Rajna | H68: Anchal Off white/blue dupatta salwar, red wine salwar, Anchal black salwar | I68: Completed
A69: 46011 | B69: Nalini | C69: 1400 | D69: Gpay | E69: Rajna | H69: Tie & Dye Rani Pink | I69: Completed
A70: 46011 | B70: Anoop | C70: 1400 | D70: Cash | E70: Anoop | H70: gift(Khadi/Salwars) - White violet salwar, Khadi | I70: Completed
A71: 46011 | B71: Ranju | C71: 1400 | D71: Cash | E71: Rajna | H71: gift(Khadi/Salwars) - Khadi | I71: Completed
A72: 46011 | B72: Girija | C72: 3700 | D72: Gpay | E72: Rajna | H72: Viscose Rayan Saree, Banarasi Chikku green, Khadi, Rayon multi colored Salwar(XL) | I72: Completed
A73: 46011 | B73: Malu | C73: 4529 | D73: Cash | E73: Anoop | H73: Golden Banarasi, Cotton Silk (contrast colors), Kalyani Cotton Orange | I73: Completed
A74: 46013 | B74: Sourabhya | C74: 580 | D74: Gpay | E74: Rajna | F74: XL | H74: Jute Kurti | I74: Completed
A75: 46013 | B75: Shajeena (TVM) | C75: 1380 | D75: Gpay | E75: Rajna | H75: Banarasi Chikku | I75: Completed
A76: 46017 | B76: Vijina (Kannur) | C76: 1380 | D76: Gpay | E76: Rajna | H76: Banarasi Golden Yellow | I76: Completed
A77: 46017 | B77: Nisha Nair (Alappuzha) | C77: 1380 | D77: Gpay | E77: Rajna | H77: Parrot Green Banarasi | I77: Completed
A78: 46017 | B78: Silpa | C78: 690 | D78: Cash | E78: Rajna | H78: Banarasi Saree - Biscuit | I78: Completed
A79: 46017 | B79: Silpa | C79: 690 | D79: Cash | E79: Anoop | H79: Banarasi Saree - Biscuit | I79: Completed
A80: 46020 | B80: Indu | C80: 3200 | D80: Gpay | E80: Rajna | H80: Aanchal Salwars | I80: Completed
A81: 46024 | B81: Shiji | C81: 2750 | D81: Gpay | E81: Rajna | H81: Banarasi parrot green, vneck peach(L) | I81: Completed
A82: 46024 | B82: Lathika | C82: 1400 | D82: Gpay | E82: Rajna | H82: Indig blue salwar (L) | I82: Completed
A83: 46024 | B83: Sushitha | C83: 1600 | D83: Gpay | E83: Rajna | H83: Roman Silk(XL) | I83: Completed
A84: 46024 | B84: Rameez | C84: 1200 | D84: Gpay | E84: Rameez | H84: Off white saree | I84: Completed
A85: 46027 | B85: Shidhin | C85: 1250 | D85: Gpay | E85: Rajna | H85: Plus size white salwar - XXXL | I85: Completed
A86: 46028 | B86: Aswathy (TVM) | C86: 1380 | D86: Gpay | E86: Rajna | H86: Biscuit Banarasi | I86: Completed
... A145: 46120 | B145: Rajna | C145: 730 | D145: Cash | E145: Rajna | H145: Tant mix bank - peacock blue | I145: Completed
A146: 46122 | B146: Saranya Gopalakrishnan(Hyd) | C146: 2430 | E146: Rajna | H146: Tussar silk Green(CHR-70) - 500 advance, Tissue silk non floral(CHR-148) | I146: Pending
A147: 46122 | B147: Jitha Joy | C147: 650 | D147: Gpay | E147: Rajna | H147: Cotton blend saree yellow - CHR-67 | I147: Completed
A148: 46122 | B148: Deepa Rajan | C148: 500 | D148: Cash | E148: Rajna | H148: Mulmul cotton black - CHR-65 | I148: Completed
A149: 46122 | B149: Latha | C149: 1250 | E149: Rajna | H149: Sungudi (Alice Christy inspired) | I149: Pending

Sheet INVENTORY
A1: SKU | B1: Item Name | C1: Category | D1: Purchase Price (₹) | E1: Sale Amount (₹) | F1: Qty Sold | G1: Qty Pending | H1: Qty Purchased | I1: Cost per Item (₹) | J1: Cost of Sold (₹) | K1: Stock Value (₹) | L1: Buyer | M1: Partner Received | N1: Status | O1: Size | P1: Color | Q1: Comments | R1: Brand | S1: Material | T1: Discount
A2: CHR-1 | B2: Black Saree | C2: Saree | D2: 779 | E2: 1250 | F2: 1 | G2: 0 | H2: =F2+IF(LEN(G2)=0,0,G2) -> 1 | I2: =IF(D2<>"",D2,IFERROR(E2/(IFERROR(SUM(Sales!C:C),0))*(IFERROR(SUM(Purchases!C:C),0)),0)) -> 779 | J2: =F2*I2 -> 779 | K2: =IF(LEN(G2)=0,0,G2)*I2 -> 0 | L2: Chris | M2: Rajna | N2: Sold Out
A3: CHR-2 | B3: Imported Rayon Salwar Black | C3: Saree | D3: 1096 | E3: 1600 | F3: 1 | G3: 0 | H3: =F3+IF(LEN(G3)=0,0,G3) -> 1 | I3: =IF(D3<>"",D3,IFERROR(E3/(IFERROR(SUM(Sales!C:C),0))*(IFERROR(SUM(Purchases!C:C),0)),0)) -> 1096 | J3: =F3*I3 -> 1096 | K3: =IF(LEN(G3)=0,0,G3)*I3 -> 0 | L3: Susmitha | M3: Rajna | N3: Sold Out
A4: CHR-3 | B4: Cotton Silk | C4: Saree | D4: 1048 | E4: 2000 | F4: 1 | G4: 0 | H4: =F4+IF(LEN(G4)=0,0,G4) -> 1 | I4: =IF(D4<>"",D4,IFERROR(E4/(IFERROR(SUM(Sales!C:C),0))*(IFERROR(SUM(Purchases!C:C),0)),0)) -> 1048 | J4: =F4*I4 -> 1048 | K4: =IF(LEN(G4)=0,0,G4)*I4 -> 0 | L4: Sreejesh | M4: Rajna | N4: Sold Out
A5: CHR-4 | B5: Silk Saree | C5: Saree | D5: 887 | E5: 1600 | F5: 1 | G5: 0 | H5: =F5+IF(LEN(G5)=0,0,G5) -> 1 | I5: =IF(D5<>"",D5,IFERROR(E5/(IFERROR(SUM(Sales!C:C),0))*(IFERROR(SUM(Purchases!C:C),0)),0)) -> 887 | J5: =F5*I5 -> 887 | K5: =IF(LEN(G5)=0,0,G5)*I5 -> 0 | L5: Latha | M5: Rajna | N5: Sold Out
A6: CHR-5 | B6: Light weight cotton | C6: Saree | D6: 372 | E6: 750 | F6: 1 | G6: 0 | H6: =F6+IF(LEN(G6)=0,0,G6) -> 1 | I6: =IF(D6<>"",D6,IFERROR(E6/(IFERROR(SUM(Sales!C:C),0))*(IFERROR(SUM(Purchases!C:C),0)),0)) -> 372 | J6: =F6*I6 -> 372 | K6: =IF(LEN(G6)=0,0,G6)*I6 -> 0 | L6: Beena (Knr), Sudhisha | M6: Rajna | N6: Sold Out
A7: CHR-6 | B7: Saree USA print (step photo) | C7: Saree | D7: 625 | E7: 1000 | F7: 1 | G7: 0 | H7: =F7+IF(LEN(G7)=0,0,G7) -> 1 | I7: =IF(D7<>"",D7,IFERROR(E7/(IFERROR(SUM(Sales!C:C),0))*(IFERROR(SUM(Purchases!C:C),0)),0)) -> 625 | J7: =F7*I7 -> 625 | K7: =IF(LEN(G7)=0,0,G7)*I7 -> 0 | L7: Binoy | M7: Rajna | N7: Sold Out
A8: CHR-7 | B8: Saree 95 1 | C8: Saree | D8: 1559 | E8: 2600 | F8: 1 | G8: 0 | H8: =F8+IF(LEN(G8)=0,0,G8) -> 1 | I8: =IF(D8<>"",D8,IFERROR(E8/(IFERROR(SUM(Sales!C:C),0))*(IFERROR(SUM(Purchases!C:C),0)),0)) -> 1559 | J8: =F8*I8 -> 1559 | K8: =IF(LEN(G8)=0,0,G8)*I8 -> 0 | L8: Binoy | M8: Rajna | N8: Sold Out
A9: CHR-8 | B9: Linen Block Print Salwar Set | C9: Salwar | D9: 839 | E9: 1000 | F9: 1 | G9: 0 | H9: =F9+IF(LEN(G9)=0,0,G9) -> 1 | I9: =IF(D9<>"",D9,IFERROR(E9/(IFERROR(SUM(Sales!C:C),0))*(IFERROR(SUM(Purchases!C:C),0)),0)) -> 839 | J9: =F9*I9 -> 839 | K9: =IF(LEN(G9)=0,0,G9)*I9 -> 0 | L9: Binoy | M9: Rajna | N9: Sold Out
A10: CHR-9 | B10: Cotton Silk | C10: Saree | D10: 1148 | E10: 2000 | F10: 1 | G10: 0 | H10: =F10+IF(LEN(G10)=0,0,G10) -> 1 | I10: =IF(D10<>"",D10,IFERROR(E10/(IFERROR(SUM(Sales!C:C),0))*(IFERROR(SUM(Purchases!C:C),0)),0)) -> 1148 | J10: =F10*I10 -> 1148 | K10: =IF(LEN(G10)=0,0,G10)*I10 -> 0 | L10: Suresh (PVB) | M10: Rajna | N10: Sold Out
A11: CHR-10 | B11: Black red banarasi | C11: Saree | D11: 1252 | E11: 1800 | F11: 2 | G11: 0 | H11: =F11+IF(LEN(G11)=0,0,G11) -> 2 | I11: =IF(D11<>"",D11,IFERROR(E11/(IFERROR(SUM(Sales!C:C),0))*(IFERROR(SUM(Purchases!C:C),0)),0)) -> 1252 | J11: =F11*I11 -> 2504 | K11: =IF(LEN(G11)=0,0,G11)*I11 -> 0 | L11: Raji, Jisha | M11: Rajna | N11: Sold Out
A12: CHR-11 | B12: Black Imported Rayon Set | C12: Salwar | D12: 1096 | E12: 1600 | F12: 1 | G12: 0 | H12: =F12+IF(LEN(G12)=0,0,G12) -> 1 | I12: =IF(D12<>"",D12,IFERROR(E12/(IFERROR(SUM(Sales!C:C),0))*(IFERROR(SUM(Purchases!C:C),0)),0)) -> 1096 | J12: =F12*I12 -> 1096 | K12: =IF(LEN(G12)=0,0,G12)*I12 -> 0 | L12: Raji | M12: Rajna | N12: Sold Out
A13: CHR-12 | B13: Imported Rayon Salwar Set Red | C13: Salwar | D13: 1096 | E13: 1600 | F13: 1 | G13: 0 | H13: =F13+IF(LEN(G13)=0,0,G13) -> 1 | I13: =IF(D13<>"",D13,IFERROR(E13/(IFERROR(SUM(Sales!C:C),0))*(IFERROR(SUM(Purchases!C:C),0)),0)) -> 1096 | J13: =F13*I13 -> 1096 | K13: =IF(LEN(G13)=0,0,G13)*I13 -> 0 | L13: Divya | M13: Rajna | N13: Sold Out
... A43: CHR-42 | B43: Linen Floral Salwar Set (sunflower) | C43: Salwar | D43: 839 | E43: 950 | F43: 1 | G43: 0 | H43: =F43+IF(LEN(G43)=0,0,G43) -> 1 | I43: =IF(D43<>"",D43,IFERROR(E43/(IFERROR(SUM(Sales!C:C),0))*(IFERROR(SUM(Purchases!C:C),0)),0)) -> 839 | J43: =F43*I43 -> 839 | K43: =IF(LEN(G43)=0,0,G43)*I43 -> 0 | L43: Yassar | M43: Rajna | N43: Sold Out
A44: CHR-43 | B44: Black Soft Cotton Flared Salwar Set | C44: Salwar | D44: 1165 | E44: 1500 | F44: 2 | G44: 0 | H44: =F44+IF(LEN(G44)=0,0,G44) -> 2 | I44: =IF(D44<>"",D44,IFERROR(E44/(IFERROR(SUM(Sales!C:C),0))*(IFERROR(SUM(Purchases!C:C),0)),0)) -> 1165 | J44: =F44*I44 -> 2330 | K44: =IF(LEN(G44)=0,0,G44)*I44 -> 0 | L44: Anju, Ranju | M44: Rajna | N44: Sold Out | O44: XXL | Q44: XXL pending
A45: CHR-44 | B45: Green & black cotton silk | C45: Saree | D45: 1048 | E45: 1900 | F45: 1 | G45: 0 | H45: =F45+IF(LEN(G45)=0,0,G45) -> 1 | I45: =IF(D45<>"",D45,IFERROR(E45/(IFERROR(SUM(Sales!C:C),0))*(IFERROR(SUM(Purchases!C:C),0)),0)) -> 1048 | J45: =F45*I45 -> 1048 | K45: =IF(LEN(G45)=0,0,G45)*I45 -> 0 | L45: Anju | M45: Rajna | N45: Sold Out
A46: CHR-45 | B46: Cotton Peach | C46: Saree | D46: 372 | E46: 650 | F46: 1 | G46: 0 | H46: =F46+IF(LEN(G46)=0,0,G46) -> 1 | I46: =IF(D46<>"",D46,IFERROR(E46/(IFERROR(SUM(Sales!C:C),0))*(IFERROR(SUM(Purchases!C:C),0)),0)) -> 372 | J46: =F46*I46 -> 372 | K46: =IF(LEN(G46)=0,0,G46)*I46 -> 0 | L46: Anju | M46: Rajna | N46: Sold Out
A47: CHR-46 | B47: Tusser embroidary saress | C47: Saree | D47: 1094 | E47: 1400 | F47: 4 | G47: 1 | H47: =F47+IF(LEN(G47)=0,0,G47) -> 5 | I47: =IF(D47<>"",D47,IFERROR(E47/(IFERROR(SUM(Sales!C:C),0))*(IFERROR(SUM(Purchases!C:C),0)),0)) -> 1094 | J47: =F47*I47 -> 4376 | K47: =IF(LEN(G47)=0,0,G47)*I47 -> 1094 | L47: Anju, Annie(2-blue/green) | M47: Rajna/Rameez | N47: Partially Sold
A48: CHR-47 | B48: Mal Chanderi | C48: Saree | D48: 779 | E48: 1000 | F48: 1 | G48: 0 | H48: =F48+IF(LEN(G48)=0,0,G48) -> 1 | I48: =IF(D48<>"",D48,IFERROR(E48/(IFERROR(SUM(Sales!C:C),0))*(IFERROR(SUM(Purchases!C:C),0)),0)) -> 779 | J48: =F48*I48 -> 779 | K48: =IF(LEN(G48)=0,0,G48)*I48 -> 0 | L48: Anju | M48: Rajna | N48: Sold Out
A49: CHR-48 | B49: Pink Tussar Emb | C49: Saree | D49: 895 | E49: 1400 | F49: 1 | G49: 0 | H49: =F49+IF(LEN(G49)=0,0,G49) -> 1 | I49: =IF(D49<>"",D49,IFERROR(E49/(IFERROR(SUM(Sales!C:C),0))*(IFERROR(SUM(Purchases!C:C),0)),0)) -> 895 | J49: =F49*I49 -> 895 | K49: =IF(LEN(G49)=0,0,G49)*I49 -> 0 | L49: Anju | M49: Rajna | N49: Sold Out | P49: Pink
A50: CHR-49 | B50: Soft Cotton Salwar set - wine red | C50: Salwar | D50: 1145 | E50: 1400 | F50: 1 | G50: 0 | H50: =F50+IF(LEN(G50)=0,0,G50) -> 1 | I50: =IF(D50<>"",D50,IFERROR(E50/(IFERROR(SUM(Sales!C:C),0))*(IFERROR(SUM(Purchases!C:C),0)),0)) -> 1145 | J50: =F50*I50 -> 1145 | K50: =IF(LEN(G50)=0,0,G50)*I50 -> 0 | L50: Rameez | M50: Rajna | N50: Sold Out
A51: CHR-50 | B51: Black Soft Cotton Flared Salwar Set | C51: Salwar | D51: 1165 | E51: 1400 | F51: 1 | G51: 0 | H51: =F51+IF(LEN(G51)=0,0,G51) -> 1 | I51: =IF(D51<>"",D51,IFERROR(E51/(IFERROR(SUM(Sales!C:C),0))*(IFERROR(SUM(Purchases!C:C),0)),0)) -> 1165 | J51: =F51*I51 -> 1165 | K51: =IF(LEN(G51)=0,0,G51)*I51 -> 0 | L51: Rameez | M51: Rajna | N51: Sold Out
A52: CHR-51 | B52: Mull Cotton Floral print with lace detailing | C52: Salwar | D52: 1200 | E52: 799 | F52: 1 | G52: 3 | H52: =F52+IF(LEN(G52)=0,0,G52) -> 4 | I52: =IF(D52<>"",D52,IFERROR(E52/(IFERROR(SUM(Sales!C:C),0))*(IFERROR(SUM(Purchases!C:C),0)),0)) -> 1200 | J52: =F52*I52 -> 1200 | K52: =IF(LEN(G52)=0,0,G52)*I52 -> 3600 | L52: Jiji | N52: Partially Sold | O52: M, L, XXL | P52: Red
A53: CHR-52 | B53: Chanderi Soft Silk Salwar Set | C53: Salwar | D53: 1941 | E53: 1250 | F53: 2 | G53: 1 | H53: =F53+IF(LEN(G53)=0,0,G53) -> 3 | I53: =IF(D53<>"",D53,IFERROR(E53/(IFERROR(SUM(Sales!C:C),0))*(IFERROR(SUM(Purchases!C:C),0)),0)) -> 1941 | J53: =F53*I53 -> 3882 | K53: =IF(LEN(G53)=0,0,G53)*I53 -> 1941 | L53: Shanu - 1800, Rinsha friend - 1000 | N53: Pending | O53: XL | P53: Ocean Blue
A54: CHR-53 | B54: Hakoba Cotton Chridar | C54: Salwar | D54: 1476 | E54: 1600 | F54: 0 | G54: 2 | H54: =F54+IF(LEN(G54)=0,0,G54) -> 2 | I54: =IF(D54<>"",D54,IFERROR(E54/(IFERROR(SUM(Sales!C:C),0))*(IFERROR(SUM(Purchases!C:C),0)),0)) -> 1476 | J54: =F54*I54 -> 0 | K54: =IF(LEN(G54)=0,0,G54)*I54 -> 2952 | N54: Pending | O54: L | P54: Blue, Black | Q54: Returned
A55: CHR-54 | B55: Linen Floral Print Salwar Set | C55: Salwar | D55: 995 | E55: 1000 | F55: 1 | G55: 1 | H55: =F55+IF(LEN(G55)=0,0,G55) -> 2 | I55: =IF(D55<>"",D55,IFERROR(E55/(IFERROR(SUM(Sales!C:C),0))*(IFERROR(SUM(Purchases!C:C),0)),0)) -> 995 | J55: =F55*I55 -> 995 | K55: =IF(LEN(G55)=0,0,G55)*I55 -> 995 | L55: Sruthi(M) | M55: Rajna | N55: Partially Sold | O55: L
A56: CHR-55 | B56: Linen Block Print Salwar Set | C56: Salwar | D56: 839 | E56: 1000 | F56: 1 | G56: 0 | H56: =F56+IF(LEN(G56)=0,0,G56) -> 1 | I56: =IF(D56<>"",D56,IFERROR(E56/(IFERROR(SUM(Sales!C:C),0))*(IFERROR(SUM(Purchases!C:C),0)),0)) -> 839 | J56: =F56*I56 -> 839 | K56: =IF(LEN(G56)=0,0,G56)*I56 -> 0 | L56: Rameez | M56: Rajna | N56: Sold Out | O56: XL-XXL
A57: CHR-56 | B57: Pakistani Semi Silk Blend | C57: Salwar | D57: 1095 | E57: 1400 | F57: 0 | G57: 3 | H57: =F57+IF(LEN(G57)=0,0,G57) -> 3 | I57: =IF(D57<>"",D57,IFERROR(E57/(IFERROR(SUM(Sales!C:C),0))*(IFERROR(SUM(Purchases!C:C),0)),0)) -> 1095 | J57: =F57*I57 -> 0 | K57: =IF(LEN(G57)=0,0,G57)*I57 -> 3285 | N57: Pending | O57: M-XL
A58: CHR-57 | B58: Linen Floral Salwar Set (yellow) | C58: Salwar | D58: 839 | E58: 1000 | F58: 0 | G58: 2 | H58: =F58+IF(LEN(G58)=0,0,G58) -> 2 | I58: =IF(D58<>"",D58,IFERROR(E58/(IFERROR(SUM(Sales!C:C),0))*(IFERROR(SUM(Purchases!C:C),0)),0)) -> 839 | J58: =F58*I58 -> 0 | K58: =IF(LEN(G58)=0,0,G58)*I58 -> 1678 | N58: Pending | O58: L, XL
A59: CHR-58 | B59: Soft Cotton Salwar set - wine red | C59: Salwar | D59: 1145 | E59: 1500 | F59: 1 | G59: 2 | H59: =F59+IF(LEN(G59)=0,0,G59) -> 3 | I59: =IF(D59<>"",D59,IFERROR(E59/(IFERROR(SUM(Sales!C:C),0))*(IFERROR(SUM(Purchases!C:C),0)),0)) -> 1145 | J59: =F59*I59 -> 1145 | K59: =IF(LEN(G59)=0,0,G59)*I59 -> 2290 | L59: Sruthi (1300) - L | N59: Partially Sold | O59: M, XL | P59: Wine red
A60: CHR-59 | B60: Silk Blend Salwar Set | C60: Salwar | D60: 1080 | E60: 1400 | F60: 1 | G60: 1 | H60: =F60+IF(LEN(G60)=0,0,G60) -> 2 | I60: =IF(D60<>"",D60,IFERROR(E60/(IFERROR(SUM(Sales!C:C),0))*(IFERROR(SUM(Purchases!C:C),0)),0)) -> 1080 | J60: =F60*I60 -> 1080 | K60: =IF(LEN(G60)=0,0,G60)*I60 -> 1080 | L60: Jisha (XL), Rameez Relative(L): 900 | M60: Rajna | N60: Sold Out | P60: Maroon, Violet
A61: CHR-60 | B61: Imported Rayon Salwar Set | C61: Salwar | D61: 1096 | E61: 1600 | F61: 2 | G61: 4 | H61: =F61+IF(LEN(G61)=0,0,G61) -> 6 | I61: =IF(D61<>"",D61,IFERROR(E61/(IFERROR(SUM(Sales!C:C),0))*(IFERROR(SUM(Purchases!C:C),0)),0)) -> 1096 | J61: =F61*I61 -> 2192 | K61: =IF(LEN(G61)=0,0,G61)*I61 -> 4384 | L61: Deepthi - Mustard for Hokoba return | N61: Partially Sold | O61: M/XL | P61: Violet(M&XL), Pink | Q61: Peacock blue sold, grey returned
A62: CHR-61 | B62: Cotton Saree | C62: Saree | D62: 562 | E62: 750 | F62: 1 | G62: 1 | H62: =F62+IF(LEN(G62)=0,0,G62) -> 2 | I62: =IF(D62<>"",D62,IFERROR(E62/(IFERROR(SUM(Sales!C:C),0))*(IFERROR(SUM(Purchases!C:C),0)),0)) -> 562 | J62: =F62*I62 -> 562 | K62: =IF(LEN(G62)=0,0,G62)*I62 -> 562 | L62: Resmi(Tvm) - 500 | N62: Partially Sold
A63: CHR-62 | B63: Silk Saree | C63: Saree | D63: 525 | E63: 700 | F63: 1 | G63: 0 | H63: =F63+IF(LEN(G63)=0,0,G63) -> 1 | I63: =IF(D63<>"",D63,IFERROR(E63/(IFERROR(SUM(Sales!C:C),0))*(IFERROR(SUM(Purchases!C:C),0)),0)) -> 525 | J63: =F63*I63 -> 525 | K63: =IF(LEN(G63)=0,0,G63)*I63 -> 0 | L63: Dona | N63: Sold Out
A64: CHR-63 | B64: Silk Saree | C64: Saree | D64: 972 | E64: 1600 | F64: 1 | G64: 0 | H64: =F64+IF(LEN(G64)=0,0,G64) -> 1 | I64: =IF(D64<>"",D64,IFERROR(E64/(IFERROR(SUM(Sales!C:C),0))*(IFERROR(SUM(Purchases!C:C),0)),0)) -> 972 | J64: =F64*I64 -> 972 | K64: =IF(LEN(G64)=0,0,G64)*I64 -> 0 | L64: Aruna | N64: Sold Out
A65: CHR-64 | B65: Kota Linen Saree | C65: Saree | D65: 1602 | E65: 1800 | F65: 0 | G65: 1 | H65: =F65+IF(LEN(G65)=0,0,G65) -> 1 | I65: =IF(D65<>"",D65,IFERROR(E65/(IFERROR(SUM(Sales!C:C),0))*(IFERROR(SUM(Purchases!C:C),0)),0)) -> 1602 | J65: =F65*I65 -> 0 | K65: =IF(LEN(G65)=0,0,G65)*I65 -> 1602 | N65: Pending
A66: CHR-65 | B66: Mulmul Cotton Collection | C66: Saree | D66: 779 | E66: 900 | F66: 2 | G66: 2 | H66: =F66+IF(LEN(G66)=0,0,G66) -> 4 | I66: =IF(D66<>"",D66,IFERROR(E66/(IFERROR(SUM(Sales!C:C),0))*(IFERROR(SUM(Purchases!C:C),0)),0)) -> 779 | J66: =F66*I66 -> 1558 | K66: =IF(LEN(G66)=0,0,G66)*I66 -> 1558 | L66: Athulya (blued and white), Rinsha (violet & pink -850) | N66: Partially Sold
A67: CHR-66 | B67: Mul Chanderi Saree with Ajrakh Palu | C67: Saree | D67: 633 | E67: 1400 | F67: 0 | G67: 0 | H67: =F67+IF(LEN(G67)=0,0,G67) -> 0 | I67: =IF(D67<>"",D67,IFERROR(E67/(IFERROR(SUM(Sales!C:C),0))*(IFERROR(SUM(Purchases!C:C),0)),0)) -> 633 | J67: =F67*I67 -> 0 | K67: =IF(LEN(G67)=0,0,G67)*I67 -> 0 | N67: Sold Out
A68: CHR-67 | B68: Cotton Blend Saree | C68: Saree | D68: 685 | E68: 1200 | F68: 1 | G68: 1 | H68: =F68+IF(LEN(G68)=0,0,G68) -> 2 | I68: =IF(D68<>"",D68,IFERROR(E68/(IFERROR(SUM(Sales!C:C),0))*(IFERROR(SUM(Purchases!C:C),0)),0)) -> 685 | J68: =F68*I68 -> 685 | K68: =IF(LEN(G68)=0,0,G68)*I68 -> 685 | L68: Jitha Joy - 650 | N68: Partially Sold | P68: Green/Yellow available
A69: CHR-68 | B69: Soft Muslin Cotton Chridar | C69: Salwar | D69: 1700 | E69: 1700 | F69: 0 | G69: 4 | H69: =F69+IF(LEN(G69)=0,0,G69) -> 4 | I69: =IF(D69<>"",D69,IFERROR(E69/(IFERROR(SUM(Sales!C:C),0))*(IFERROR(SUM(Purchases!C:C),0)),0)) -> 1700 | J69: =F69*I69 -> 0 | K69: =IF(LEN(G69)=0,0,G69)*I69 -> 6800 | N69: Pending | O69: M-XXL
A70: CHR-69 | B70: Cotton Silk (Green & dusty mauve) | C70: Saree | D70: 1148 | E70: 1399 | F70: 2 | G70: 0 | H70: =F70+IF(LEN(G70)=0,0,G70) -> 2 | I70: =IF(D70<>"",D70,IFERROR(E70/(IFERROR(SUM(Sales!C:C),0))*(IFERROR(SUM(Purchases!C:C),0)),0)) -> 1148 | J70: =F70*I70 -> 2296 | K70: =IF(LEN(G70)=0,0,G70)*I70 -> 0 | L70: Simi (TVM), Saranya Gopalakrishanan (pending-1250) | N70: Sold Out
A71: CHR-70 | B71: Tussar Silk | C71: Saree | D71: 857 | E71: 900 | F71: 3 | G71: 0 | H71: =F71+IF(LEN(G71)=0,0,G71) -> 3 | I71: =IF(D71<>"",D71,IFERROR(E71/(IFERROR(SUM(Sales!C:C),0))*(IFERROR(SUM(Purchases!C:C),0)),0)) -> 857 | J71: =F71*I71 -> 2571 | K71: =IF(LEN(G71)=0,0,G71)*I71 -> 0 | L71: Susmi. Shinoob (Teal blue), Sarany Hyd -980 | M71: Rajna | N71: Sold Out | P71: Green
A72: CHR-71 | B72: Cotton Silk (contrast colors) | C72: Saree | D72: 1198 | E72: 1900 | F72: 1 | G72: 0 | H72: =F72+IF(LEN(G72)=0,0,G72) -> 1 | I72: =IF(D72<>"",D72,IFERROR(E72/(IFERROR(SUM(Sales!C:C),0))*(IFERROR(SUM(Purchases!C:C),0)),0)) -> 1198 | J72: =F72*I72 -> 1198 | K72: =IF(LEN(G72)=0,0,G72)*I72 -> 0 | L72: Malu | N72: Sold Out
A73: CHR-72 | B73: Black 2 pice Rayon | C73: Salwar | D73: 525 | E73: 800 | F73: 1 | G73: 0 | H73: =F73+IF(LEN(G73)=0,0,G73) -> 1 | I73: =IF(D73<>"",D73,IFERROR(E73/(IFERROR(SUM(Sales!C:C),0))*(IFERROR(SUM(Purchases!C:C),0)),0)) -> 525 | J73: =F73*I73 -> 525 | K73: =IF(LEN(G73)=0,0,G73)*I73 -> 0 | L73: Nishitha | N73: Sold Out
A74: CHR-73 | B74: Linen Blend Saree | C74: Saree | D74: 450 | E74: 600 | F74: 1 | G74: 0 | H74: =F74+IF(LEN(G74)=0,0,G74) -> 1 | I74: =IF(D74<>"",D74,IFERROR(E74/(IFERROR(SUM(Sales!C:C),0))*(IFERROR(SUM(Purchases!C:C),0)),0)) -> 450 | J74: =F74*I74 -> 450 | K74: =IF(LEN(G74)=0,0,G74)*I74 -> 0 | L74: Asha Rose | M74: Rajna | N74: Sold Out
A75: CHR-74 | B75: Linen Floral Salwar Set | C75: Salwar | D75: 1000 | E75: 1000 | F75: 1 | G75: 0 | H75: =F75+IF(LEN(G75)=0,0,G75) -> 1 | I75: =IF(D75<>"",D75,IFERROR(E75/(IFERROR(SUM(Sales!C:C),0))*(IFERROR(SUM(Purchases!C:C),0)),0)) -> 1000 | J75: =F75*I75 -> 1000 | K75: =IF(LEN(G75)=0,0,G75)*I75 -> 0 | L75: Asha Rose | M75: Rajna | N75: Sold Out
A76: CHR-75 | B76: Linen Buti | C76: Saree | D76: 1900 | E76: 1900 | F76: 1 | G76: 0 | H76: =F76+IF(LEN(G76)=0,0,G76) -> 1 | I76: =IF(D76<>"",D76,IFERROR(E76/(IFERROR(SUM(Sales!C:C),0))*(IFERROR(SUM(Purchases!C:C),0)),0)) -> 1900 | J76: =F76*I76 -> 1900 | K76: =IF(LEN(G76)=0,0,G76)*I76 -> 0 | L76: Susmi | M76: Rajna | N76: Sold Out
A77: CHR-76 | B77: Soft cotton white and blue printed salwar suit set (plus size) | C77: Salwar | D77: 995 | E77: 1500 | F77: 1 | G77: 2 | H77: =F77+IF(LEN(G77)=0,0,G77) -> 3 | I77: =IF(D77<>"",D77,IFERROR(E77/(IFERROR(SUM(Sales!C:C),0))*(IFERROR(SUM(Purchases!C:C),0)),0)) -> 995 | J77: =F77*I77 -> 995 | K77: =IF(LEN(G77)=0,0,G77)*I77 -> 1990 | L77: Shidhin (XXXL-1250) | N77: Partially Sold | O77: Size: XL, XXL
A78: CHR-77 | B78: Chanderi silk soft dusty rose/pink kurta suit set with delicate floral prints and light embroiderysalwar 3 piece set | C78: Salwar | D78: 1075 | E78: 1560 | F78: 2 | G78: 2 | H78: =F78+IF(LEN(G78)=0,0,G78) -> 4 | I78: =IF(D78<>"",D78,IFERROR(E78/(IFERROR(SUM(Sales!C:C),0))*(IFERROR(SUM(Purchases!C:C),0)),0)) -> 1075 | J78: =F78*I78 -> 2150 | K78: =IF(LEN(G78)=0,0,G78)*I78 -> 2150 | L78: Saida (1400), Binija (1560) | N78: Partially Sold | O78: Size: M, L
A79: CHR-78 | B79: Linen blend deep wine/maroon kurta suit with elegant embroidery and a contrasting dupatta | C79: Salwar | D79: 1045 | E79: 1495 | F79: 0 | G79: 1 | H79: =F79+IF(LEN(G79)=0,0,G79) -> 1 | I79: =IF(D79<>"",D79,IFERROR(E79/(IFERROR(SUM(Sales!C:C),0))*(IFERROR(SUM(Purchases!C:C),0)),0)) -> 1045 | J79: =F79*I79 -> 0 | K79: =IF(LEN(G79)=0,0,G79)*I79 -> 1045 | N79: New | O79: Size: M
A80: CHR-79 | B80: Silk blend 3 piece salwar set(indigo blue) | C80: Salwar | D80: 1230 | E80: 1700 | F80: 2 | G80: 2 | H80: =F80+IF(LEN(G80)=0,0,G80) -> 4 | I80: =IF(D80<>"",D80,IFERROR(E80/(IFERROR(SUM(Sales!C:C),0))*(IFERROR(SUM(Purchases!C:C),0)),0)) -> 1230 | J80: =F80*I80 -> 2460 | K80: =IF(LEN(G80)=0,0,G80)*I80 -> 2460 | L80: Saida (1600), Lathika (L-1400) | N80: Partially Sold | O80: Size: M, XXL
A81: CHR-80 | B81: Rayon multicolored printed kurta set with a bold and artistic patchwork-style | C81: Salwar | D81: 595 | E81: 890 | F81: 3 | G81: 0 | H81: =F81+IF(LEN(G81)=0,0,G81) -> 3 | I81: =IF(D81<>"",D81,IFERROR(E81/(IFERROR(SUM(Sales!C:C),0))*(IFERROR(SUM(Purchases!C:C),0)),0)) -> 595 | J81: =F81*I81 -> 1785 | K81: =IF(LEN(G81)=0,0,G81)*I81 -> 0 | L81: Dilna (XL) Girija (L), Amma (XXL) | N81: Sold Out
A82: CHR-81 | B82: Soft cotton salwar 3 piece set - coral pink | C82: Salwar | D82: 1075 | E82: 1545 | F82: 3 | G82: 0 | H82: =F82+IF(LEN(G82)=0,0,G82) -> 3 | I82: =IF(D82<>"",D82,IFERROR(E82/(IFERROR(SUM(Sales!C:C),0))*(IFERROR(SUM(Purchases!C:C),0)),0)) -> 1075 | J82: =F82*I82 -> 3225 | K82: =IF(LEN(G82)=0,0,G82)*I82 -> 0 | L82: Jisha (1545-XL), Shiji(1370-L), Sheejamol(XXL)-850 | N82: Sold Out
A83: CHR-82 | B83: Soft cotton with white embroidery/sequence work incl shall (3 piece, beige) | C83: Salwar | D83: 1004 | E83: 1495 | F83: 3 | G83: 0 | H83: =F83+IF(LEN(G83)=0,0,G83) -> 3 | I83: =IF(D83<>"",D83,IFERROR(E83/(IFERROR(SUM(Sales!C:C),0))*(IFERROR(SUM(Purchases!C:C),0)),0)) -> 1004 | J83: =F83*I83 -> 3012 | K83: =IF(LEN(G83)=0,0,G83)*I83 -> 0 | L83: Jisha (XL - 1455), Shinoob friend (L) (1400), Divya ordered - XXL (1400) | N83: Sold Out | O83: Size: L, XL, XXL
A84: CHR-83 | B84: Co-ord set short (2 piece) linen blend | C84: Salwar | D84: 450 | E84: 650 | F84: 1 | G84: 2 | H84: =F84+IF(LEN(G84)=0,0,G84) -> 3 | I84: =IF(D84<>"",D84,IFERROR(E84/(IFERROR(SUM(Sales!C:C),0))*(IFERROR(SUM(Purchases!C:C),0)),0)) -> 450 | J84: =F84*I84 -> 450 | K84: =IF(LEN(G84)=0,0,G84)*I84 -> 900 | L84: Silpa (600) - M | N84: Partially Sold | O84: Size: L, XL
A85: CHR-84 | B85: Soft cotton salwar 3 piece set (Indigo/royal blue) Ajrakh print | C85: Salwar | D85: 895 | E85: 1350 | F85: 2 | G85: 1 | H85: =F85+IF(LEN(G85)=0,0,G85) -> 3 | I85: =IF(D85<>"",D85,IFERROR(E85/(IFERROR(SUM(Sales!C:C),0))*(IFERROR(SUM(Purchases!C:C),0)),0)) -> 895 | J85: =F85*I85 -> 1790 | K85: =IF(LEN(G85)=0,0,G85)*I85 -> 895 | L85: Susmi (M), Susheela(Kannur)XL-950 | N85: Partially Sold | O85: XXL
A86: CHR-85 | B86: Linen Blend cotton Salwar Set- 3 piece (lavender with ajrakh print) | C86: Salwar | D86: 1045 | E86: 1495 | F86: 2 | G86: 2 | H86: =F86+IF(LEN(G86)=0,0,G86) -> 4 | I86: =IF(D86<>"",D86,IFERROR(E86/(IFERROR(SUM(Sales!C:C),0))*(IFERROR(SUM(Purchases!C:C),0)),0)) -> 1045 | J86: =F86*I86 -> 2090 | K86: =IF(LEN(G86)=0,0,G86)*I86 -> 2090 | L86: Baby Khadeeja - 1400, Rameez Relative(XXL): 900 | N86: Partially Sold | O86: Size: M, L
A87: CHR-86 | B87: Soft cotton buble work salwar - 3 piece set (mustard) | C87: Salwar | D87: 1195 | E87: 1670 | F87: 1 | G87: 2 | H87: =F87+IF(LEN(G87)=0,0,G87) -> 3 | I87: =IF(D87<>"",D87,IFERROR(E87/(IFERROR(SUM(Sales!C:C),0))*(IFERROR(SUM(Purchases!C:C),0)),0)) -> 1195 | J87: =F87*I87 -> 1195 | K87: =IF(LEN(G87)=0,0,G87)*I87 -> 2390 | N87: New | O87: Size: M, L,XL
A88: CHR-87 | B88: Cotton printed Salwar Set - 3 piece (brick red with black elephant) | C88: Salwar | D88: 795 | E88: 1200 | F88: 3 | G88: 1 | H88: =F88+IF(LEN(G88)=0,0,G88) -> 4 | I88: =IF(D88<>"",D88,IFERROR(E88/(IFERROR(SUM(Sales!C:C),0))*(IFERROR(SUM(Purchases!C:C),0)),0)) -> 795 | J88: =F88*I88 -> 2385 | K88: =IF(LEN(G88)=0,0,G88)*I88 -> 795 | L88: Susmi (1200) - L Sreelakshmi (1000) - XL, Prema (1000) - XXL | N88: Partially Sold | O88: Size - M,XXL
A89: CHR-88 | B89: Cotton silk saree in green and black | C89: Saree | D89: 1048 | E89: 1200 | F89: 1 | G89: 1 | H89: =F89+IF(LEN(G89)=0,0,G89) -> 2 | I89: =IF(D89<>"",D89,IFERROR(E89/(IFERROR(SUM(Sales!C:C),0))*(IFERROR(SUM(Purchases!C:C),0)),0)) -> 1048 | J89: =F89*I89 -> 1048 | K89: =IF(LEN(G89)=0,0,G89)*I89 -> 1048 | L89: Shinoob - 1100 | N89: Partially Sold
A90: CHR-89 | B90: Banarasi Silk black & pink | C90: Saree | D90: 1195 | E90: 1450 | F90: 1 | G90: 0 | H90: =F90+IF(LEN(G90)=0,0,G90) -> 1 | I90: =IF(D90<>"",D90,IFERROR(E90/(IFERROR(SUM(Sales!C:C),0))*(IFERROR(SUM(Purchases!C:C),0)),0)) -> 1195 | J90: =F90*I90 -> 1195 | K90: =IF(LEN(G90)=0,0,G90)*I90 -> 0 | L90: Rinsha | N90: Sold Out
A91: CHR-90 | B91: Rainbow saree | C91: saree | D91: 389 | E91: 689 | F91: 1 | G91: 1 | H91: =F91+IF(LEN(G91)=0,0,G91) -> 2 | I91: =IF(D91<>"",D91,IFERROR(E91/(IFERROR(SUM(Sales!C:C),0))*(IFERROR(SUM(Purchases!C:C),0)),0)) -> 389 | J91: =F91*I91 -> 389 | K91: =IF(LEN(G91)=0,0,G91)*I91 -> 389 | L91: Latha (500) | N91: New
A92: CHR-91 | B92: Tissue Silk | C92: saree | D92: 489 | E92: 789 | F92: 3 | G92: 0 | H92: =F92+IF(LEN(G92)=0,0,G92) -> 3 | I92: =IF(D92<>"",D92,IFERROR(E92/(IFERROR(SUM(Sales!C:C),0))*(IFERROR(SUM(Purchases!C:C),0)),0)) -> 489 | J92: =F92*I92 -> 1467 | K92: =IF(LEN(G92)=0,0,G92)*I92 -> 0 | L92: Athulya (brick red)-789, Annie-600(Yellow), Rajitha (Peach)-500 | N92: Sold Out
A93: CHR-92 | B93: Kurti blue Jute | C93: Kurti | D93: 472 | E93: 650 | F93: 1 | G93: 2 | H93: =F93+IF(LEN(G93)=0,0,G93) -> 3 | I93: =IF(D93<>"",D93,IFERROR(E93/(IFERROR(SUM(Sales!C:C),0))*(IFERROR(SUM(Purchases!C:C),0)),0)) -> 472 | J93: =F93*I93 -> 472 | K93: =IF(LEN(G93)=0,0,G93)*I93 -> 944 | L93: Sourabhya (XL - 580) | N93: Partially Sold | O93: L, XXL
A94: CHR-93 | B94: banarasi silk saree | C94: Saree | D94: 892 | E94: 1400 | F94: 1 | G94: 0 | H94: =F94+IF(LEN(G94)=0,0,G94) -> 1 | I94: =IF(D94<>"",D94,IFERROR(E94/(IFERROR(SUM(Sales!C:C),0))*(IFERROR(SUM(Purchases!C:C),0)),0)) -> 892 | J94: =F94*I94 -> 892 | K94: =IF(LEN(G94)=0,0,G94)*I94 -> 0 | L94: Haseena | N94: Sold Out
A95: CHR-94 | B95: Khadi stripe saree | C95: Saree | D95: 340 | E95: 600 | F95: 3 | G95: 0 | H95: =F95+IF(LEN(G95)=0,0,G95) -> 3 | I95: =IF(D95<>"",D95,IFERROR(E95/(IFERROR(SUM(Sales!C:C),0))*(IFERROR(SUM(Purchases!C:C),0)),0)) -> 340 | J95: =F95*I95 -> 1020 | K95: =IF(LEN(G95)=0,0,G95)*I95 -> 0 | L95: Nalini, Latha, Girija | N95: Sold Out
A96: CHR-95 | B96: Chinon silk saree | C96: Saree | D96: 1250 | E96: 1450 | F96: 0 | G96: 1 | H96: =F96+IF(LEN(G96)=0,0,G96) -> 1 | I96: =IF(D96<>"",D96,IFERROR(E96/(IFERROR(SUM(Sales!C:C),0))*(IFERROR(SUM(Purchases!C:C),0)),0)) -> 1250 | J96: =F96*I96 -> 0 | K96: =IF(LEN(G96)=0,0,G96)*I96 -> 1250 | N96: New
A97: CHR-96 | B97: Pashmina silk saree | C97: Saree | D97: 1250 | E97: 1450 | F97: 1 | G97: 0 | H97: =F97+IF(LEN(G97)=0,0,G97) -> 1 | I97: =IF(D97<>"",D97,IFERROR(E97/(IFERROR(SUM(Sales!C:C),0))*(IFERROR(SUM(Purchases!C:C),0)),0)) -> 1250 | J97: =F97*I97 -> 1250 | K97: =IF(LEN(G97)=0,0,G97)*I97 -> 0 | L97: Aruna | N97: Sold Out
A98: CHR-97 | B98: Aanchal - Black and whit salawar | C98: Salwar | D98: 1300 | E98: 1500 | F98: 1 | G98: 0 | H98: =F98+IF(LEN(G98)=0,0,G98) -> 1 | I98: =IF(D98<>"",D98,IFERROR(E98/(IFERROR(SUM(Sales!C:C),0))*(IFERROR(SUM(Purchases!C:C),0)),0)) -> 1300 | J98: =F98*I98 -> 1300 | K98: =IF(LEN(G98)=0,0,G98)*I98 -> 0 | L98: Yassar | N98: Sold Out | O98: L
A99: CHR-98 | B99: Aanchal - Red Salwar with black flowers | C99: Salwar | D99: 1160 | E99: 1500 | F99: 1 | G99: 0 | H99: =F99+IF(LEN(G99)=0,0,G99) -> 1 | I99: =IF(D99<>"",D99,IFERROR(E99/(IFERROR(SUM(Sales!C:C),0))*(IFERROR(SUM(Purchases!C:C),0)),0)) -> 1160 | J99: =F99*I99 -> 1160 | K99: =IF(LEN(G99)=0,0,G99)*I99 -> 0 | L99: Yassar | N99: Sold Out | O99: L
A100: CHR-99 | B100: Aanchal - Red salwar with white flower | C100: Salwar | D100: 1300 | E100: 1500 | F100: 1 | G100: 0 | H100: =F100+IF(LEN(G100)=0,0,G100) -> 1 | I100: =IF(D100<>"",D100,IFERROR(E100/(IFERROR(SUM(Sales!C:C),0))*(IFERROR(SUM(Purchases!C:C),0)),0)) -> 1300 | J100: =F100*I100 -> 1300 | K100: =IF(LEN(G100)=0,0,G100)*I100 -> 0 | L100: Yassar | N100: Sold Out | O100: L
A101: CHR-100 | B101: Aanchal yellow salwar | C101: Salwar | D101: 1622 | E101: 1900 | F101: 1 | G101: 0 | H101: =F101+IF(LEN(G101)=0,0,G101) -> 1 | I101: =IF(D101<>"",D101,IFERROR(E101/(IFERROR(SUM(Sales!C:C),0))*(IFERROR(SUM(Purchases!C:C),0)),0)) -> 1622 | J101: =F101*I101 -> 1622 | K101: =IF(LEN(G101)=0,0,G101)*I101 -> 0 | L101: Shimna | N101: Sold Out | O101: L
A102: CHR-101 | B102: Aanchal blue Salwar with white lining (bagru hand printed) | C102: Salwar | D102: 1092 | E102: 1500 | F102: 1 | G102: 0 | H102: =F102+IF(LEN(G102)=0,0,G102) -> 1 | I102: =IF(D102<>"",D102,IFERROR(E102/(IFERROR(SUM(Sales!C:C),0))*(IFERROR(SUM(Purchases!C:C),0)),0)) -> 1092 | J102: =F102*I102 -> 1092 | K102: =IF(LEN(G102)=0,0,G102)*I102 -> 0 | L102: Shimna | N102: Sold Out | O102: L
A103: CHR-102 | B103: Aanchal black & white floral print salwar | C103: Salwar | D103: 976 | E103: 1399 | F103: 1 | G103: 0 | H103: =F103+IF(LEN(G103)=0,0,G103) -> 1 | I103: =IF(D103<>"",D103,IFERROR(E103/(IFERROR(SUM(Sales!C:C),0))*(IFERROR(SUM(Purchases!C:C),0)),0)) -> 976 | J103: =F103*I103 -> 976 | K103: =IF(LEN(G103)=0,0,G103)*I103 -> 0 | L103: Sruthi | N103: Sold Out | O103: L
A104: CHR-103 | B104: Aanchal navy blue cotton kurta with red embriodered detailing | C104: Salwar | D104: 976 | E104: 1600 | F104: 1 | G104: 0 | H104: =F104+IF(LEN(G104)=0,0,G104) -> 1 | I104: =IF(D104<>"",D104,IFERROR(E104/(IFERROR(SUM(Sales!C:C),0))*(IFERROR(SUM(Purchases!C:C),0)),0)) -> 976 | J104: =F104*I104 -> 976 | K104: =IF(LEN(G104)=0,0,G104)*I104 -> 0 | L104: Indu | N104: Sold Out | O104: L
A105: CHR-104 | B105: Aanchal black Salwar with white printex work | C105: Salwar | D105: 976 | E105: 1600 | F105: 1 | G105: 0 | H105: =F105+IF(LEN(G105)=0,0,G105) -> 1 | I105: =IF(D105<>"",D105,IFERROR(E105/(IFERROR(SUM(Sales!C:C),0))*(IFERROR(SUM(Purchases!C:C),0)),0)) -> 976 | J105: =F105*I105 -> 976 | K105: =IF(LEN(G105)=0,0,G105)*I105 -> 0 | L105: Indu | N105: Sold Out | O105: L
A106: CHR-105 | B106: Aanchal navy blue embroidered Pakistani Aghanoor cotton 3-piece set | C106: Salwar | D106: 976 | E106: 1600 | F106: 0 | G106: 1 | H106: =F106+IF(LEN(G106)=0,0,G106) -> 1 | I106: =IF(D106<>"",D106,IFERROR(E106/(IFERROR(SUM(Sales!C:C),0))*(IFERROR(SUM(Purchases!C:C),0)),0)) -> 976 | J106: =F106*I106 -> 0 | K106: =IF(LEN(G106)=0,0,G106)*I106 -> 976 | N106: Pending | O106: L
A107: CHR-106 | B107: Aanchal green floral print cotton salwar set | C107: Salwar | D107: 976 | E107: 1400 | F107: 1 | G107: 0 | H107: =F107+IF(LEN(G107)=0,0,G107) -> 1 | I107: =IF(D107<>"",D107,IFERROR(E107/(IFERROR(SUM(Sales!C:C),0))*(IFERROR(SUM(Purchases!C:C),0)),0)) -> 976 | J107: =F107*I107 -> 976 | K107: =IF(LEN(G107)=0,0,G107)*I107 -> 0 | L107: Dona | N107: Sold Out | O107: L
A108: CHR-107 | B108: Aanchal black ajrakh hand block printed salwar set | C108: Salwar | D108: 976 | E108: 1600 | F108: 1 | G108: 0 | H108: =F108+IF(LEN(G108)=0,0,G108) -> 1 | I108: =IF(D108<>"",D108,IFERROR(E108/(IFERROR(SUM(Sales!C:C),0))*(IFERROR(SUM(Purchases!C:C),0)),0)) -> 976 | J108: =F108*I108 -> 976 | K108: =IF(LEN(G108)=0,0,G108)*I108 -> 0 | L108: Aasa | N108: Sold Out | O108: L
A109: CHR-108 | B109: Aanchal Rani cotton salwar | C109: Salwar | D109: 976 | E109: 1500 | F109: 1 | G109: 0 | H109: =F109+IF(LEN(G109)=0,0,G109) -> 1 | I109: =IF(D109<>"",D109,IFERROR(E109/(IFERROR(SUM(Sales!C:C),0))*(IFERROR(SUM(Purchases!C:C),0)),0)) -> 976 | J109: =F109*I109 -> 976 | K109: =IF(LEN(G109)=0,0,G109)*I109 -> 0 | L109: Shimna | N109: Sold Out | O109: L
A110: CHR-109 | B110: Aanchal Blue & red cotton Azrakh print | C110: Salwar | D110: 976 | E110: 1600 | F110: 1 | G110: 0 | H110: =F110+IF(LEN(G110)=0,0,G110) -> 1 | I110: =IF(D110<>"",D110,IFERROR(E110/(IFERROR(SUM(Sales!C:C),0))*(IFERROR(SUM(Purchases!C:C),0)),0)) -> 976 | J110: =F110*I110 -> 976 | K110: =IF(LEN(G110)=0,0,G110)*I110 -> 0 | L110: Pramitha | N110: Sold Out | O110: L
A111: CHR-110 | B111: Aanchal white Anarkali Salwar | C111: Salwar | D111: 976 | E111: 1600 | F111: 1 | G111: 0 | H111: =F111+IF(LEN(G111)=0,0,G111) -> 1 | I111: =IF(D111<>"",D111,IFERROR(E111/(IFERROR(SUM(Sales!C:C),0))*(IFERROR(SUM(Purchases!C:C),0)),0)) -> 976 | J111: =F111*I111 -> 976 | K111: =IF(LEN(G111)=0,0,G111)*I111 -> 0 | L111: Aasa | N111: Sold Out | O111: L
A112: CHR-111 | B112: Aanchal Cotton white salwar set | C112: Salwar | D112: 976 | E112: 1600 | F112: 0 | G112: 1 | H112: =F112+IF(LEN(G112)=0,0,G112) -> 1 | I112: =IF(D112<>"",D112,IFERROR(E112/(IFERROR(SUM(Sales!C:C),0))*(IFERROR(SUM(Purchases!C:C),0)),0)) -> 976 | J112: =F112*I112 -> 0 | K112: =IF(LEN(G112)=0,0,G112)*I112 -> 976 | N112: New | O112: L
A113: CHR-112 | B113: Aanchal beige cotton salwar with navy blue block-print dupatta | C113: Salwar | D113: 976 | E113: 1300 | F113: 1 | G113: 0 | H113: =F113+IF(LEN(G113)=0,0,G113) -> 1 | I113: =IF(D113<>"",D113,IFERROR(E113/(IFERROR(SUM(Sales!C:C),0))*(IFERROR(SUM(Purchases!C:C),0)),0)) -> 976 | J113: =F113*I113 -> 976 | K113: =IF(LEN(G113)=0,0,G113)*I113 -> 0 | L113: Sruthi | N113: Sold Out | O113: L
A114: CHR-113 | B114: Viscose Rayon Silk Saree (Cocoa brown) | C114: Saree | D114: 1118.26 | E114: 1500 | F114: 1 | G114: 0 | H114: =F114+IF(LEN(G114)=0,0,G114) -> 1 | I114: =IF(D114<>"",D114,IFERROR(E114/(IFERROR(SUM(Sales!C:C),0))*(IFERROR(SUM(Purchases!C:C),0)),0)) -> 1118.26 | J114: =F114*I114 -> 1118.26 | K114: =IF(LEN(G114)=0,0,G114)*I114 -> 0 | L114: Girija | N114: Sold Out
A115: CHR-114 | B115: Viscose Georgette Saree | C115: Saree | D115: 1254.76 | E115: 1599 | F115: 5 | G115: 0 | H115: =F115+IF(LEN(G115)=0,0,G115) -> 5 | I115: =IF(D115<>"",D115,IFERROR(E115/(IFERROR(SUM(Sales!C:C),0))*(IFERROR(SUM(Purchases!C:C),0)),0)) -> 1254.76 | J115: =F115*I115 -> 6273.8 | K115: =IF(LEN(G115)=0,0,G115)*I115 -> 0 | L115: Amalu(black/maroon), Lethy(Thiruvalla):1550, Vineet(Maroon): 1550, Chris(Yellow) - 1250, Geemol (Black/Violet) - 1500 | N115: Sold Out
A116: CHR-115 | B116: Banarasi Silk | C116: Saree | D116: 891.5 | E116: 1400 | F116: 20 | G116: 1 | H116: =F116+IF(LEN(G116)=0,0,G116) -> 21 | I116: =IF(D116<>"",D116,IFERROR(E116/(IFERROR(SUM(Sales!C:C),0))*(IFERROR(SUM(Purchases!C:C),0)),0)) -> 891.5 | J116: =F116*I116 -> 17830 | K116: =IF(LEN(G116)=0,0,G116)*I116 -> 891.5 | L116: Biscuit - Aruna, Silpa, Malini, Aswathi, Resmi(Thrissur), Asha(Navaikulam), Ambika Preman (Pazhanji), Anitha(Pathanamthitta),salini(kottayam) vinod(kottayam), Laks Pillai Yellow green - Aasa, Jyothi Chikku green - Girija Blue blue - Aruna Golden yellow - Malu Golden Yellow - Vijina, Preethi Thomas Pink - Ambika Preman (Pazhanji) | N116: Partially Sold | P116: Rust orange - 1
A117: CHR-116 | B117: Banarasi Silk (Yellow design) | C117: Saree | D117: 891.46 | E117: 1400 | F117: 1 | G117: 0 | H117: =F117+IF(LEN(G117)=0,0,G117) -> 1 | I117: =IF(D117<>"",D117,IFERROR(E117/(IFERROR(SUM(Sales!C:C),0))*(IFERROR(SUM(Purchases!C:C),0)),0)) -> 891.46 | J117: =F117*I117 -> 891.46 | K117: =IF(LEN(G117)=0,0,G117)*I117 -> 0 | L117: Rishma | N117: Sold Out
A118: CHR-117 | B118: Chanderi Silk Tie & Dye collection | C118: Saree | D118: 1047.9 | E118: 1500 | F118: 1 | G118: 1 | H118: =F118+IF(LEN(G118)=0,0,G118) -> 2 | I118: =IF(D118<>"",D118,IFERROR(E118/(IFERROR(SUM(Sales!C:C),0))*(IFERROR(SUM(Purchases!C:C),0)),0)) -> 1047.9 | J118: =F118*I118 -> 1047.9 | K118: =IF(LEN(G118)=0,0,G118)*I118 -> 1047.9 | L118: Nalini - Pink (1400) | N118: Partially Sold | P118: Blue - 1
A119: CHR-118 | B119: Off-white block-printed silk saree | C119: Saree | D119: 870.46 | E119: 1200 | F119: 1 | G119: 0 | H119: =F119+IF(LEN(G119)=0,0,G119) -> 1 | I119: =IF(D119<>"",D119,IFERROR(E119/(IFERROR(SUM(Sales!C:C),0))*(IFERROR(SUM(Purchases!C:C),0)),0)) -> 870.46 | J119: =F119*I119 -> 870.46 | K119: =IF(LEN(G119)=0,0,G119)*I119 -> 0 | L119: Rameez | N119: Sold Out
A120: CHR-119 | B120: Chanderi Printed Silk Saree | C120: Saree | D120: 418.95333 | E120: 699 | F120: 3 | G120: 2 | H120: =F120+IF(LEN(G120)=0,0,G120) -> 5 | I120: =IF(D120<>"",D120,IFERROR(E120/(IFERROR(SUM(Sales!C:C),0))*(IFERROR(SUM(Purchases!C:C),0)),0)) -> 418.95333 | J120: =F120*I120 -> 1256.86 | K120: =IF(LEN(G120)=0,0,G120)*I120 -> 837.90667 | L120: Aruna - violet, Resmi - navy blue, Malini - Rani Pink | M120: Rajna | N120: Partially Sold | P120: Violet, navy blue, rani pink
A121: CHR-120 | B121: Kalyani cotton silk | C121: Saree | D121: 817.95 | E121: 1249 | F121: 2 | G121: 0 | H121: =F121+IF(LEN(G121)=0,0,G121) -> 2 | I121: =IF(D121<>"",D121,IFERROR(E121/(IFERROR(SUM(Sales!C:C),0))*(IFERROR(SUM(Purchases!C:C),0)),0)) -> 817.95 | J121: =F121*I121 -> 1635.9 | K121: =IF(LEN(G121)=0,0,G121)*I121 -> 0 | L121: Aruna - Yellow, Malu - Orange (Pending) | N121: Sold Out | P121: yellow green & orange green
A122: CHR-121 | B122: Roman Silk Salwar Set | C122: Salwar | D122: 1175 | E122: 1600 | F122: 1 | G122: 3 | H122: =F122+IF(LEN(G122)=0,0,G122) -> 4 | I122: =IF(D122<>"",D122,IFERROR(E122/(IFERROR(SUM(Sales!C:C),0))*(IFERROR(SUM(Purchases!C:C),0)),0)) -> 1175 | J122: =F122*I122 -> 1175 | K122: =IF(LEN(G122)=0,0,G122)*I122 -> 3525 | L122: Sushitha (XXL-1600) | N122: Partially Sold | O122: M, L, XL
A123: CHR-122 | B123: Banarasi Silk (Parrot Green) | C123: Saree | D123: 891.44 | E123: 1380 | F123: 5 | G123: 0 | H123: =F123+IF(LEN(G123)=0,0,G123) -> 5 | I123: =IF(D123<>"",D123,IFERROR(E123/(IFERROR(SUM(Sales!C:C),0))*(IFERROR(SUM(Purchases!C:C),0)),0)) -> 891.44 | J123: =F123*I123 -> 4457.2 | K123: =IF(LEN(G123)=0,0,G123)*I123 -> 0 | L123: Nisha Nair Shiji Priya Reji Raji Nisha Sajitha | N123: Sold Out
A124: CHR-123 | B124: Kalyani cotton silk (red) | C124: Saree | D124: 807.452 | E124: 1249 | F124: 5 | G124: 0 | H124: =F124+IF(LEN(G124)=0,0,G124) -> 5 | I124: =IF(D124<>"",D124,IFERROR(E124/(IFERROR(SUM(Sales!C:C),0))*(IFERROR(SUM(Purchases!C:C),0)),0)) -> 807.452 | J124: =F124*I124 -> 4037.26 | K124: =IF(LEN(G124)=0,0,G124)*I124 -> 0 | L124: Divya (Kollam), Ananya (TVM), Liji (Vadakara), Archana(Devagiri)-Ordered, Anu(Kottayam), Linu(Kottayam) | N124: Sold Out | P124: Red
A125: CHR-124 | B125: Viscose Chokda | C125: Saree | D125: 908.25 | E125: 1450 | F125: 2 | G125: 0 | H125: =F125+IF(LEN(G125)=0,0,G125) -> 2 | I125: =IF(D125<>"",D125,IFERROR(E125/(IFERROR(SUM(Sales!C:C),0))*(IFERROR(SUM(Purchases!C:C),0)),0)) -> 908.25 | J125: =F125*I125 -> 1816.5 | K125: =IF(LEN(G125)=0,0,G125)*I125 -> 0 | L125: Neethu(Pkd)-1450, Remya(Pkd)-1250 | N125: Sold Out | P125: Blue, Green
A126: CHR-125 | B126: Aanchal Maroon Salwar | C126: Salwar | D126: 1760 | E126: 1800 | F126: 1 | G126: 0 | H126: =F126+IF(LEN(G126)=0,0,G126) -> 1 | I126: =IF(D126<>"",D126,IFERROR(E126/(IFERROR(SUM(Sales!C:C),0))*(IFERROR(SUM(Purchases!C:C),0)),0)) -> 1760 | J126: =F126*I126 -> 1760 | K126: =IF(LEN(G126)=0,0,G126)*I126 -> 0 | L126: Malu (1800) | N126: Sold Out | O126: XXXL
A127: CHR-126 | B127: Aanchal maroon palzo kurta | C127: Salwar | D127: 1330 | E127: 1650 | F127: 1 | G127: 0 | H127: =F127+IF(LEN(G127)=0,0,G127) -> 1 | I127: =IF(D127<>"",D127,IFERROR(E127/(IFERROR(SUM(Sales!C:C),0))*(IFERROR(SUM(Purchases!C:C),0)),0)) -> 1330 | J127: =F127*I127 -> 1330 | K127: =IF(LEN(G127)=0,0,G127)*I127 -> 0 | L127: Seeniya | N127: Sold Out | O127: L
A128: CHR-127 | B128: ⁠Rustic Geo Kota (Stairs) - Net Kota | C128: Saree | D128: 1155 | E128: 1650 | F128: 0 | G128: 1 | H128: =F128+IF(LEN(G128)=0,0,G128) -> 1 | I128: =IF(D128<>"",D128,IFERROR(E128/(IFERROR(SUM(Sales!C:C),0))*(IFERROR(SUM(Purchases!C:C),0)),0)) -> 1155 | J128: =F128*I128 -> 0 | K128: =IF(LEN(G128)=0,0,G128)*I128 -> 1155 | N128: New
A129: CHR-128 | B129: ⁠Grey Arrow Kota (Arrow) - Net kota | C129: Saree | D129: 1155 | E129: 1650 | F129: 1 | G129: 0 | H129: =F129+IF(LEN(G129)=0,0,G129) -> 1 | I129: =IF(D129<>"",D129,IFERROR(E129/(IFERROR(SUM(Sales!C:C),0))*(IFERROR(SUM(Purchases!C:C),0)),0)) -> 1155 | J129: =F129*I129 -> 1155 | K129: =IF(LEN(G129)=0,0,G129)*I129 -> 0 | L129: Chris (1250) | N129: Sold Out
...

Sheet PartnerShares
A1: Partner Settings
A2: Partner | B2: Share %
A3: Rajna | B3: 0.3334
A4: Anoop | B4: 0.3332
A5: Rameez | B5: 0.3334
A7: Partner | B7: Total Purchases (Contributions) | C7: Target Contributions (by %) | D7: Contribution Over/(Under) | E7: Profit Share (Completed Only) | F7: Net Before Settlements | G7: Net Settlements (Received - Paid) | H7: Net Position After Settlements
A8: Rajna | B8: =IFERROR(SUMIF(Purchases!$B:$B,$A8,Purchases!$C:$C),0) -> 126654 | C8: =SUM($B$8:$B$10)/3 -> 98145.333 | D8: =B8-C8 -> 28508.667 | E8: =IF(Summary!$B$6>0, Summary!$B$6*VLOOKUP($A8,$A$3:$B$5,2,FALSE()),0) -> 0 | F8: =D8+E8 -> 28508.667 | G8: =IFERROR(SUMIFS($E$13:$E$499,$D$13:$D$499,$A8,$B$13:$B$499,"Contribution"),0)+IFERROR(SUMIFS($E$13:$E$499,$D$13:$D$499,$A8,$B$13:$B$499,"Profit"),0)-IFERROR(SUMIFS($E$13:$E$499,$C$13:$C$499,$A8,$B$13:$B$499,"Contribution"),0)-IFERROR(SUMIFS($E$13:$E$499,$C$13:$C$499,$A8,$B$13:$B$499,"Profit"),0) -> 18303.34 | H8: =F8-G8 -> 10205.327
A9: Anoop | B9: =IFERROR(SUMIF(Purchases!$B:$B,$A9,Purchases!$C:$C),0) -> 135182 | C9: =SUM($B$8:$B$10)/3 -> 98145.333 | D9: =B9-C9 -> 37036.667 | E9: =IF(Summary!$B$6>0, Summary!$B$6*VLOOKUP($A9,$A$3:$B$5,2,FALSE()),0) -> 0 | F9: =D9+E9 -> 37036.667 | G9: =IFERROR(SUMIFS($E$13:$E$499,$D$13:$D$499,$A9,$B$13:$B$499,"Contribution"),0)+IFERROR(SUMIFS($E$13:$E$499,$D$13:$D$499,$A9,$B$13:$B$499,"Profit"),0)-IFERROR(SUMIFS($E$13:$E$499,$C$13:$C$499,$A9,$B$13:$B$499,"Contribution"),0)-IFERROR(SUMIFS($E$13:$E$499,$C$13:$C$499,$A9,$B$13:$B$499,"Profit"),0) -> 41639.33 | H9: =F9-G9 -> -4602.6633
A10: Rameez | B10: =IFERROR(SUMIF(Purchases!$B:$B,$A10,Purchases!$C:$C),0) -> 32600 | C10: =SUM($B$8:$B$10)/3 -> 98145.333 | D10: =B10-C10 -> -65545.333 | E10: =IF(Summary!$B$6>0, Summary!$B$6*VLOOKUP($A10,$A$3:$B$5,2,FALSE()),0) -> 0 | F10: =D10+E10 -> -65545.333 | G10: =IFERROR(SUMIFS($E$13:$E$499,$D$13:$D$499,$A10,$B$13:$B$499,"Contribution"),0)+IFERROR(SUMIFS($E$13:$E$499,$D$13:$D$499,$A10,$B$13:$B$499,"Profit"),0)-IFERROR(SUMIFS($E$13:$E$499,$C$13:$C$499,$A10,$B$13:$B$499,"Contribution"),0)-IFERROR(SUMIFS($E$13:$E$499,$C$13:$C$499,$A10,$B$13:$B$499,"Profit"),0) -> -59942.67 | H10: =F10-G10 -> -5602.6633
A12: Global Settlements Log (used for Contributions, Cash Pool & Profit)
A13: Date | B13: Type (Contribution/Cash/Profit) | C13: From Partner | D13: To Partner | E13: Amount (₹) | F13: Notes
A14: 45952 | B14: Contribution | C14: Rameez | D14: Rajna | E14: 16032
A15: 45952 | B15: Contribution | C15: Rameez | D15: Anoop | E15: 21859
A16: 45954 | B16: Cash | C16: Rajna | D16: Rameez | E16: 28826.524
A17: 45954 | B17: Cash | C17: Rajna | D17: Anoop | E17: 32606.952
A18: 45970 | B18: Contribution | C18: Anoop | D18: Rameez | E18: 3209.34
A19: 45970 | B19: Contribution | C19: Anoop | D19: Rajna | E19: 411
A20: 45973 | B20: Contribution | C20: Anoop | D20: Rameez | E20: 905
A21: 45973 | B21: Contribution | C21: Rajna | D21: Rameez | E21: 904
A22: 46058 | B22: Contribution | C22: Rameez | D22: Anoop | E22: 27014
A23: 46059 | B23: Cash | C23: Rajna | D23: Rameez | E23: 30266
A24: 46059 | B24: Contribution | C24: Rajna | D24: Anoop | E24: 2225
A25: 46059 | B25: Cash | C25: Rajna | D25: Anoop | E25: 32354
... A29: 46093 | B29: Cash | C29: Rajna | D29: Anoop | E29: 6626.09

Sheet Cash Pool
A1: Cash Pool Overview (Completed Sales Only)
A3: Partner | B3: Cash Collected (Completed Sales) | C3: Share % | D3: Target Cash Based on % | E3: Over/(Under) Collection | F3: Net Cash Settlements (Received - Paid) | G3: Cash Position After Settlements
A4: Rajna | B4: =IFERROR(SUMIFS(Sales!$C:$C,Sales!$E:$E,$A4,Sales!$I:$I,"Completed"),0) -> 235543 | C4: =VLOOKUP($A4,PartnerShares!$A$3:$B$5,2,FALSE()) -> 0.3334 | D4: =Summary!$B$4*C4 -> 85514.433 | E4: =B4-D4 -> 150028.57 | F4: =IFERROR(SUMIFS(PartnerShares!$E$13:$E$499,PartnerShares!$D$13:$D$499,$A4,PartnerShares!$B$13:$B$499,"Cash"),0)-IFERROR(SUMIFS(PartnerShares!$E$13:$E$499,PartnerShares!$C$13:$C$499,$A4,PartnerShares!$B$13:$B$499,"Cash"),0) -> -137310.03 | G4: =E4+F4 -> 12718.541
A5: Anoop | B5: =IFERROR(SUMIFS(Sales!$C:$C,Sales!$E:$E,$A5,Sales!$I:$I,"Completed"),0) -> 8419 | C5: =VLOOKUP($A5,PartnerShares!$A$3:$B$5,2,FALSE()) -> 0.3332 | D5: =Summary!$B$4*C5 -> 85463.134 | E5: =B5-D5 -> -77044.134 | F5: =IFERROR(SUMIFS(PartnerShares!$E$13:$E$499,PartnerShares!$D$13:$D$499,$A5,PartnerShares!$B$13:$B$499,"Cash"),0)-IFERROR(SUMIFS(PartnerShares!$E$13:$E$499,PartnerShares!$C$13:$C$499,$A5,PartnerShares!$B$13:$B$499,"Cash"),0) -> 71587.042 | G5: =E5+F5 -> -5457.0924
A6: Rameez | B6: =IFERROR(SUMIFS(Sales!$C:$C,Sales!$E:$E,$A6,Sales!$I:$I,"Completed"),0) -> 12530 | C6: =VLOOKUP($A6,PartnerShares!$A$3:$B$5,2,FALSE()) -> 0.3334 | D6: =Summary!$B$4*C6 -> 85514.433 | E6: =B6-D6 -> -72984.433 | F6: =IFERROR(SUMIFS(PartnerShares!$E$13:$E$499,PartnerShares!$D$13:$D$499,$A6,PartnerShares!$B$13:$B$499,"Cash"),0)-IFERROR(SUMIFS(PartnerShares!$E$13:$E$499,PartnerShares!$C$13:$C$499,$A6,PartnerShares!$B$13:$B$499,"Cash"),0) -> 65722.984 | G6: =E6+F6 -> -7261.4488
A9: Notes:
A10: 1. Cash Collected only counts sales with Status = "Completed".
A11: 2. Target Cash is based on the same partner percentages as profit sharing.
A12: 3. Over/(Under) is the raw difference before any cash settlements.
A13: 4. Net Cash Settlements reads Type = "Cash" rows from PartnerShares Settlements Log.
A14: 5. Cash Position After Settlements = Over/(Under) + Net Cash Settlements.
